[{"name":"Denis","login":"denislukoianov","password":"qazwssx","id":1610912114495},{"name":"Valery","login":"lerasipakova","password":"rfvtgb","id":1610912143100},{"name":"Max","login":"maxshahov","password":"wsxrfv","id":1610989416132},{"name":"Lag","login":"maxsh","password":"wsxrfv","id":1610990638216},{"name":"Lagff","login":"maxshff","password":"wsxrfv34s","id":1610990784113},{"name":"Lagff","login":"max1234","password":"wsxrfddv34s","id":1610991416438},{"name":"Lena","login":"poiuy","password":"$2b$10$8KDu1eQqz6wnnFSc/1OJyOO/QD2Kcnc0SDXCr37WAYUTeyNt/p8zO","id":1610991555786},{"name":"Yan","login":"yandradon","password":"rutigkc","id":1611001203729},{"name":"Yancfs","login":"yandrrr","password":"rutigkcfds","id":1611001252704},{"name":"Yasd","login":"dendd","password":"$2b$10$aOgR/57CRmVFS2UHM2zzmuIOqtuThH.eyEAuSzEWdc6eo8DjnDuIq","id":1611001358476},{"name":"Default","login":"default","password":"$2b$10$5/uJzkNAZViqzVimPP/qj.U5pu8ds2xcjaUnCZJ.zGrF2BGnO2Hga","id":1611004096592}]